libximc/__init__.py
libximc/highlevel/__init__.py
libximc/highlevel/_flag_enumerations.py
libximc/highlevel/_highlevel.py
libximc/highlevel/_structure_types.py
libximc/library-files/debian-amd64/libbindy.so
libximc/library-files/debian-amd64/libjximc.so
libximc/library-files/debian-amd64/libjximc.so.7
libximc/library-files/debian-amd64/libjximc.so.7.0.0
libximc/library-files/debian-amd64/libximc.a
libximc/library-files/debian-amd64/libximc.so
libximc/library-files/debian-amd64/libximc.so.7
libximc/library-files/debian-amd64/libximc.so.7.0.0
libximc/library-files/debian-amd64/libxiwrapper.so
libximc/library-files/debian-armhf/libbindy.so
libximc/library-files/debian-armhf/libjximc.so
libximc/library-files/debian-armhf/libjximc.so.7
libximc/library-files/debian-armhf/libjximc.so.7.0.0
libximc/library-files/debian-armhf/libximc.a
libximc/library-files/debian-armhf/libximc.so
libximc/library-files/debian-armhf/libximc.so.7
libximc/library-files/debian-armhf/libximc.so.7.0.0
libximc/library-files/debian-armhf/libxiwrapper.so
libximc/library-files/debian-i386/libbindy.so
libximc/library-files/debian-i386/libjximc.so
libximc/library-files/debian-i386/libjximc.so.7
libximc/library-files/debian-i386/libjximc.so.7.0.0
libximc/library-files/debian-i386/libximc.a
libximc/library-files/debian-i386/libximc.so
libximc/library-files/debian-i386/libximc.so.7
libximc/library-files/debian-i386/libximc.so.7.0.0
libximc/library-files/debian-i386/libxiwrapper.so
libximc/library-files/win32/bindy.dll
libximc/library-files/win32/bindy.lib
libximc/library-files/win32/libjximc.dll
libximc/library-files/win32/libximc.dll
libximc/library-files/win32/libximc.lib
libximc/library-files/win32/ximcnet.dll
libximc/library-files/win32/xiwrapper.dll
libximc/library-files/win64/bindy.dll
libximc/library-files/win64/bindy.lib
libximc/library-files/win64/libjximc.dll
libximc/library-files/win64/libximc.dll
libximc/library-files/win64/libximc.lib
libximc/library-files/win64/ximcnet.dll
libximc-2.14.28.dist-info/METADATA
libximc-2.14.28.dist-info/WHEEL
libximc-2.14.28.dist-info/licenses/LICENSE
libximc-2.14.28.dist-info/RECORD
