Metadata-Version: 2.1
Name: libximc
Version: 2.14.28
Summary: Package for operating STANDA 8SMC5 controllers
Author-email: STANDA LTD <8smc4@standa.lt>
License: Copyright (c) 2023 STANDA LTD
License-File: LICENSE
Classifier: License :: OSI Approved :: MIT License
Classifier: Operating System :: OS Independent
Classifier: Programming Language :: Python :: 3
Requires-Python: >=3.6
